{"/":{"bundle.90447.css":{"type":"style","weight":1},"bundle.5c8fa.esm.js":{"type":"script","weight":1}},"/class.page":{"bundle.90447.css":{"type":"style","weight":1},"bundle.5c8fa.esm.js":{"type":"script","weight":1},"route-class.page.chunk.cde9f.esm.js":{"type":"script","weight":0.9},"route-class.page.chunk.cd7c6.css":{"type":"style","weight":0.9}},"/profile":{"bundle.90447.css":{"type":"style","weight":1},"bundle.5c8fa.esm.js":{"type":"script","weight":1},"route-profile.chunk.57a24.esm.js":{"type":"script","weight":0.9},"route-profile.chunk.0289b.css":{"type":"style","weight":0.9}},"/search":{"bundle.90447.css":{"type":"style","weight":1},"bundle.5c8fa.esm.js":{"type":"script","weight":1},"route-search.chunk.f4e1b.esm.js":{"type":"script","weight":0.9},"route-search.chunk.bba84.css":{"type":"style","weight":0.9}}}